setup.py
gsbin_probability/Binomialdistribution.py
gsbin_probability/Gaussiandistribution.py
gsbin_probability/Generaldistribution.py
gsbin_probability/__init__.py
gsbin_probability.egg-info/PKG-INFO
gsbin_probability.egg-info/SOURCES.txt
gsbin_probability.egg-info/dependency_links.txt
gsbin_probability.egg-info/not-zip-safe
gsbin_probability.egg-info/top_level.txt